Metadata-Version: 2.1
Name: roughset
Version: 0.3.0
Summary: A Python library that provides a set of tools to calculate rough sets and obtain reduct rules.
Home-page: https://github.com/Keycatowo/rough-set
Author: owo
Author-email: contact@owomail.cc
Classifier: Programming Language :: Python :: 3
Classifier: License :: OSI Approved :: MIT License
Classifier: Operating System :: OS Independent
License-File: LICENSE
Requires-Dist: pandas
